README.rst
setup.py
commonwealth/__init__.py
commonwealth/urls.py
commonwealth.egg-info/PKG-INFO
commonwealth.egg-info/SOURCES.txt
commonwealth.egg-info/dependency_links.txt
commonwealth.egg-info/top_level.txt
tests/__init__.py