Metadata-Version: 1.1
Name: commonwealth
Version: 0.0.0
Summary: Community as a Platform
Home-page: https://github.com/brwr/Commonwealth
Author: James Brewer
Author-email: james@jamesbrewer.io
License: MIT
Keywords: community platform
Platform: UNKNOWN
Classifier: Development Status :: 2 - Pre-Alpha
Classifier: Framework :: Django :: 1.8
Classifier: Intended Audience :: Education
Classifier: License :: OSI Approved :: MIT License
Classifier: Natural Language :: English
Classifier: Operating System :: POSIX :: Linux
Classifier: Programming Language :: Python :: 2.7
Classifier: Topic :: Education
Classifier: Topic :: Internet :: WWW/HTTP :: WSGI :: Application
